{
  "labels": {
    "analysis": "The MCP Server is designed to assist users in finding academic conferences based on specific keywords. It provides tools to search for events, retrieving detailed information such as event names, descriptions, dates, locations, and submission deadlines. This functionality is primarily aimed at researchers, academics, and professionals who need to stay informed about upcoming conferences to plan submissions or attendance.",
    "reasoning": "The primary label \"Web Search & Research\" is chosen because the server's core functionality revolves around searching for academic events, which is a research-oriented task. The secondary label \"Education\" is selected because the tool is specifically tailored towards academic and conference-related needs. No custom label is needed as the predefined categories adequately cover the server's functionality.",
    "primary_label": "Web Search & Research",
    "secondary_labels": [
      "Education"
    ],
    "custom_label": null,
    "is_connected": true,
    "is_remote_tool_valid": true,
    "featured_server": false
  },
  "metadata": {
    "server_id": 1661,
    "server_name": "Call For Papers",
    "rank_by_usage": 1662,
    "usage_count": "Not available",
    "original_file": "../crawler/smithery/@EmirHth_weather-forecast-mcp1.json",
    "mode": "smithery",
    "timestamp": 1751938055,
    "remote_server_response": {
      "url": "https://server.smithery.ai/@EmirHth/weather-forecast-mcp1/mcp?api_key=8675feae-43b6-4170-beb5-d8fa5a938222&profile=monetary-anteater-CCaAaT",
      "is_success": true,
      "error": null,
      "tools": [
        {
          "name": "get_events",
          "description": "Search for conferences matching specific keywords.",
          "input_schema": {
            "properties": {
              "keywords": {
                "title": "Keywords",
                "type": "string"
              },
              "limit": {
                "default": 10,
                "title": "Limit",
                "type": "integer"
              }
            },
            "required": [
              "keywords"
            ],
            "title": "get_eventsArguments",
            "type": "object"
          },
          "annotations": null
        }
      ],
      "tool_count": 1,
      "tool_names": [
        "get_events"
      ]
    },
    "server_info_crawled": {
      "id": 1661,
      "name": "Call For Papers",
      "author": "@EmirHth/weather-forecast-mcp1",
      "overview": "Search for upcoming academic conferences and events based on keywords. Retrieve detailed information including event name, description, dates, location, and submission deadlines. Easily find relevant academic conferences to plan your submissions and attendance.",
      "repository_url": "https://github.com/EmirHth/weather-forecast-mcp",
      "homepage": "https://smithery.ai/server/@EmirHth/weather-forecast-mcp1",
      "remote_or_local": "Remote",
      "license": "Smithery",
      "usage_count": "Not available",
      "success_rate": "Not available",
      "tags": [
        "search",
        "web",
        "api",
        "mcp"
      ],
      "categories": [
        "search",
        "api"
      ],
      "file_path": "../crawler/smithery/@EmirHth_weather-forecast-mcp1.json",
      "tools_count": 1,
      "tools": [
        {
          "name": "get_events",
          "description": "Search for conferences matching specific keywords.",
          "input_schema": {
            "properties": {
              "keywords": {
                "title": "Keywords",
                "type": "string"
              },
              "limit": {
                "default": 10,
                "title": "Limit",
                "type": "integer"
              }
            },
            "required": [
              "keywords"
            ],
            "title": "get_eventsArguments",
            "type": "object"
          },
          "annotations": null
        }
      ],
      "python_sdk": "import mcp\nfrom mcp.client.streamable_http import streamablehttp_client\nimport json\nimport base64\n\nsmithery_api_key = \"\"\nurl = f\"https://server.smithery.ai/@EmirHth/weather-forecast-mcp1/mcp?api_key={smithery_api_key}\"\n\nasync def main():\n    # Connect to the server using HTTP client\n    async with streamablehttp_client(url) as (read_stream, write_stream, _):\n        async with mcp.ClientSession(read_stream, write_stream) as session:\n            # Initialize the connection\n            await session.initialize()\n            # List available tools\n            tools_result = await session.list_tools()\n            print(f\"Available tools: {', '.join([t.name for t in tools_result.tools])}\")\n\nif __name__ == \"__main__\":\n    import asyncio\n    asyncio.run(main())",
      "configuration_schema": "",
      "smithery_configuration_requirements": [],
      "python_sdk_config": "",
      "python_sdk_url": "https://server.smithery.ai/@EmirHth/weather-forecast-mcp1/mcp?api_key={smithery_api_key}"
    },
    "source_filename": "1662.@EmirHth_weather-forecast-mcp1_prepared.json",
    "processed_timestamp": 1753731940,
    "processing_mode": "smithery",
    "rank": 1504
  }
}