{
  "labels": {
    "analysis": "The MCP Server is designed to facilitate database management and operations. It provides tools for connecting to various databases (PostgreSQL, MySQL, Firestore), listing tables, executing queries, setting up triggers and functions, and exporting data. The primary focus is on enabling efficient interaction with databases, making it a powerful tool for database administrators, developers, or anyone needing routine database operations.",
    "reasoning": "The primary label \"Database Operations\" is chosen because the server's core functionality revolves around database connectivity, querying, and data management. Secondary labels \"Data Analysis & Processing\" and \"Database Operations\" are included because the tools support querying and exporting data, which overlaps with data analysis tasks. No custom label is needed as the predefined categories sufficiently cover the server's functionality.",
    "primary_label": "Database Operations",
    "secondary_labels": [
      "Data Analysis & Processing"
    ],
    "custom_label": null,
    "is_connected": true,
    "is_remote_tool_valid": false,
    "featured_server": false
  },
  "metadata": {
    "server_id": 1218,
    "server_name": "Database Explorer",
    "rank_by_usage": 1219,
    "usage_count": "Not available",
    "original_file": "../crawler/smithery/@wirdes_db-mcp-tool.json",
    "mode": "smithery",
    "timestamp": 1751938055,
    "remote_server_response": {
      "url": "https://server.smithery.ai/@wirdes/db-mcp-tool/mcp?api_key=8675feae-43b6-4170-beb5-d8fa5a938222&profile=monetary-anteater-CCaAaT",
      "is_success": true,
      "error": null,
      "tools": [
        {
          "name": "!pg",
          "description": null,
          "input_schema": {
            "type": "object",
            "properties": {
              "connection": {
                "type": "object",
                "properties": {
                  "host": {
                    "type": "string"
                  },
                  "port": {
                    "type": "number"
                  },
                  "database": {
                    "type": "string"
                  },
                  "user": {
                    "type": "string"
                  },
                  "password": {
                    "type": "string"
                  }
                },
                "required": [
                  "host",
                  "database",
                  "user",
                  "password"
                ],
                "additionalProperties": false
              }
            },
            "required": [
              "connection"
            ],
            "additionalProperties": false,
            "$schema": "http://json-schema.org/draft-07/schema#"
          },
          "annotations": null
        },
        {
          "name": "!mysql",
          "description": null,
          "input_schema": {
            "type": "object",
            "properties": {
              "connection": {
                "type": "object",
                "properties": {
                  "host": {
                    "type": "string"
                  },
                  "port": {
                    "type": "number"
                  },
                  "database": {
                    "type": "string"
                  },
                  "user": {
                    "type": "string"
                  },
                  "password": {
                    "type": "string"
                  }
                },
                "required": [
                  "host",
                  "database",
                  "user",
                  "password"
                ],
                "additionalProperties": false
              }
            },
            "required": [
              "connection"
            ],
            "additionalProperties": false,
            "$schema": "http://json-schema.org/draft-07/schema#"
          },
          "annotations": null
        },
        {
          "name": "!firestore",
          "description": null,
          "input_schema": {
            "type": "object",
            "properties": {
              "connection": {
                "type": "object",
                "properties": {
                  "projectId": {
                    "type": "string"
                  },
                  "keyFilename": {
                    "type": "string"
                  }
                },
                "required": [
                  "projectId",
                  "keyFilename"
                ],
                "additionalProperties": false
              }
            },
            "required": [
              "connection"
            ],
            "additionalProperties": false,
            "$schema": "http://json-schema.org/draft-07/schema#"
          },
          "annotations": null
        },
        {
          "name": "!tables",
          "description": null,
          "input_schema": {
            "type": "object",
            "properties": {},
            "additionalProperties": false,
            "$schema": "http://json-schema.org/draft-07/schema#"
          },
          "annotations": null
        },
        {
          "name": "!triggers",
          "description": null,
          "input_schema": {
            "type": "object",
            "properties": {},
            "additionalProperties": false,
            "$schema": "http://json-schema.org/draft-07/schema#"
          },
          "annotations": null
        },
        {
          "name": "!functions",
          "description": null,
          "input_schema": {
            "type": "object",
            "properties": {},
            "additionalProperties": false,
            "$schema": "http://json-schema.org/draft-07/schema#"
          },
          "annotations": null
        },
        {
          "name": "!query",
          "description": null,
          "input_schema": {
            "type": "object",
            "properties": {
              "query": {
                "type": "string"
              }
            },
            "required": [
              "query"
            ],
            "additionalProperties": false,
            "$schema": "http://json-schema.org/draft-07/schema#"
          },
          "annotations": null
        },
        {
          "name": "!export-db",
          "description": null,
          "input_schema": {
            "type": "object",
            "properties": {
              "table": {
                "type": "string"
              }
            },
            "required": [
              "table"
            ],
            "additionalProperties": false,
            "$schema": "http://json-schema.org/draft-07/schema#"
          },
          "annotations": null
        },
        {
          "name": "!export-data",
          "description": null,
          "input_schema": {
            "type": "object",
            "properties": {
              "table": {
                "type": "string"
              }
            },
            "required": [
              "table"
            ],
            "additionalProperties": false,
            "$schema": "http://json-schema.org/draft-07/schema#"
          },
          "annotations": null
        }
      ],
      "tool_count": 9,
      "tool_names": [
        "!pg",
        "!mysql",
        "!firestore",
        "!tables",
        "!triggers",
        "!functions",
        "!query",
        "!export-db",
        "!export-data"
      ]
    },
    "server_info_crawled": {
      "id": 1218,
      "name": "Database Explorer",
      "author": "@wirdes/db-mcp-tool",
      "overview": "Connect to and manage various databases effortlessly. Execute queries, list tables, and export data with ease, enhancing your database management experience.",
      "repository_url": "https://github.com/wirdes/db-mcp-tool",
      "homepage": "https://smithery.ai/server/@wirdes/db-mcp-tool",
      "remote_or_local": "Remote",
      "license": "MIT",
      "usage_count": "Not available",
      "success_rate": "Not available",
      "tags": [
        "search",
        "web",
        "api",
        "mcp"
      ],
      "categories": [
        "search",
        "api"
      ],
      "file_path": "../crawler/smithery/@wirdes_db-mcp-tool.json",
      "tools_count": 9,
      "tools": [
        {
          "name": "!pg",
          "description": null,
          "input_schema": {
            "type": "object",
            "properties": {
              "connection": {
                "type": "object",
                "properties": {
                  "host": {
                    "type": "string"
                  },
                  "port": {
                    "type": "number"
                  },
                  "database": {
                    "type": "string"
                  },
                  "user": {
                    "type": "string"
                  },
                  "password": {
                    "type": "string"
                  }
                },
                "required": [
                  "host",
                  "database",
                  "user",
                  "password"
                ],
                "additionalProperties": false
              }
            },
            "required": [
              "connection"
            ],
            "additionalProperties": false,
            "$schema": "http://json-schema.org/draft-07/schema#"
          },
          "annotations": null
        },
        {
          "name": "!mysql",
          "description": null,
          "input_schema": {
            "type": "object",
            "properties": {
              "connection": {
                "type": "object",
                "properties": {
                  "host": {
                    "type": "string"
                  },
                  "port": {
                    "type": "number"
                  },
                  "database": {
                    "type": "string"
                  },
                  "user": {
                    "type": "string"
                  },
                  "password": {
                    "type": "string"
                  }
                },
                "required": [
                  "host",
                  "database",
                  "user",
                  "password"
                ],
                "additionalProperties": false
              }
            },
            "required": [
              "connection"
            ],
            "additionalProperties": false,
            "$schema": "http://json-schema.org/draft-07/schema#"
          },
          "annotations": null
        },
        {
          "name": "!firestore",
          "description": null,
          "input_schema": {
            "type": "object",
            "properties": {
              "connection": {
                "type": "object",
                "properties": {
                  "projectId": {
                    "type": "string"
                  },
                  "keyFilename": {
                    "type": "string"
                  }
                },
                "required": [
                  "projectId",
                  "keyFilename"
                ],
                "additionalProperties": false
              }
            },
            "required": [
              "connection"
            ],
            "additionalProperties": false,
            "$schema": "http://json-schema.org/draft-07/schema#"
          },
          "annotations": null
        },
        {
          "name": "!tables",
          "description": null,
          "input_schema": {
            "type": "object",
            "properties": {},
            "additionalProperties": false,
            "$schema": "http://json-schema.org/draft-07/schema#"
          },
          "annotations": null
        },
        {
          "name": "!triggers",
          "description": null,
          "input_schema": {
            "type": "object",
            "properties": {},
            "additionalProperties": false,
            "$schema": "http://json-schema.org/draft-07/schema#"
          },
          "annotations": null
        },
        {
          "name": "!functions",
          "description": null,
          "input_schema": {
            "type": "object",
            "properties": {},
            "additionalProperties": false,
            "$schema": "http://json-schema.org/draft-07/schema#"
          },
          "annotations": null
        },
        {
          "name": "!query",
          "description": null,
          "input_schema": {
            "type": "object",
            "properties": {
              "query": {
                "type": "string"
              }
            },
            "required": [
              "query"
            ],
            "additionalProperties": false,
            "$schema": "http://json-schema.org/draft-07/schema#"
          },
          "annotations": null
        },
        {
          "name": "!export-db",
          "description": null,
          "input_schema": {
            "type": "object",
            "properties": {
              "table": {
                "type": "string"
              }
            },
            "required": [
              "table"
            ],
            "additionalProperties": false,
            "$schema": "http://json-schema.org/draft-07/schema#"
          },
          "annotations": null
        },
        {
          "name": "!export-data",
          "description": null,
          "input_schema": {
            "type": "object",
            "properties": {
              "table": {
                "type": "string"
              }
            },
            "required": [
              "table"
            ],
            "additionalProperties": false,
            "$schema": "http://json-schema.org/draft-07/schema#"
          },
          "annotations": null
        }
      ],
      "python_sdk": "import mcp\nfrom mcp.client.streamable_http import streamablehttp_client\nimport json\nimport base64\n\nsmithery_api_key = \"\"\nurl = f\"https://server.smithery.ai/@wirdes/db-mcp-tool/mcp?api_key={smithery_api_key}\"\n\nasync def main():\n    # Connect to the server using HTTP client\n    async with streamablehttp_client(url) as (read_stream, write_stream, _):\n        async with mcp.ClientSession(read_stream, write_stream) as session:\n            # Initialize the connection\n            await session.initialize()\n            # List available tools\n            tools_result = await session.list_tools()\n            print(f\"Available tools: {', '.join([t.name for t in tools_result.tools])}\")\n\nif __name__ == \"__main__\":\n    import asyncio\n    asyncio.run(main())",
      "configuration_schema": "",
      "smithery_configuration_requirements": [],
      "python_sdk_config": "",
      "python_sdk_url": "https://server.smithery.ai/@wirdes/db-mcp-tool/mcp?api_key={smithery_api_key}"
    },
    "source_filename": "1219.@wirdes_db-mcp-tool_prepared.json",
    "processed_timestamp": 1753731940,
    "processing_mode": "smithery",
    "rank": 1173
  }
}