{
  "labels": {
    "analysis": "The MCP Server provides tools for accessing, retrieving, and navigating biblical content across multiple translations and languages. Its core functionality centers around providing quick access to Bible verses, chapters, books, and translations through a simple API interface. The server solves problems related to biblical research, content integration in applications, and easy access to scripture for educational or spiritual purposes.",
    "reasoning": "The primary label \"Religious & Spiritual\" is chosen as the server's core functionality revolves around biblical content, which is inherently religious and spiritual in nature. While tools like \"API Integration\" and \"Web Search & Research\" could be considered relevant, they are more general categories. A custom label \"Biblical Content Access\" is used to more precisely describe the server's unique purpose.",
    "primary_label": "Others",
    "secondary_labels": [
      "API Integration"
    ],
    "custom_label": "Biblical Content Access",
    "is_connected": true,
    "is_remote_tool_valid": true,
    "featured_server": false
  },
  "metadata": {
    "server_id": 462,
    "server_name": "Bible Verse Access Server",
    "rank_by_usage": 463,
    "usage_count": "40",
    "original_file": "../crawler/smithery/@HarunGuclu_bible-mcp.json",
    "mode": "smithery",
    "timestamp": 1751938055,
    "remote_server_response": {
      "url": "https://server.smithery.ai/@HarunGuclu/bible-mcp/mcp?api_key=8675feae-43b6-4170-beb5-d8fa5a938222&profile=monetary-anteater-CCaAaT",
      "is_success": true,
      "error": null,
      "tools": [
        {
          "name": "get_random_bible_verse",
          "description": "\n    Get a random Bible verse.\n\n    Args:\n        book_ids: Optional comma-separated list of book IDs (e.g., \"GEN,JHN\")\n                 or special strings \"OT\" (Old Testament) or \"NT\" (New Testament)\n\n    Returns:\n        Random verse data including reference, text, and translation info\n    ",
          "input_schema": {
            "properties": {
              "book_ids": {
                "default": null,
                "title": "Book Ids",
                "type": "string"
              }
            },
            "title": "get_random_bible_verseArguments",
            "type": "object"
          },
          "annotations": null
        },
        {
          "name": "get_bible_verse",
          "description": "\n    Get a specific Bible verse or passage.\n\n    Args:\n        reference: Bible reference (e.g., \"John 3:16\", \"Genesis 1:1-3\")\n        translation: Translation identifier (default: \"web\" for World English Bible)\n\n    Returns:\n        Verse data including reference, text, and translation info\n    ",
          "input_schema": {
            "properties": {
              "reference": {
                "title": "Reference",
                "type": "string"
              },
              "translation": {
                "default": "web",
                "title": "Translation",
                "type": "string"
              }
            },
            "required": [
              "reference"
            ],
            "title": "get_bible_verseArguments",
            "type": "object"
          },
          "annotations": null
        },
        {
          "name": "list_bible_translations",
          "description": "\n    Get list of all available Bible translations.\n\n    Returns:\n        List of available translations with their identifiers and names\n    ",
          "input_schema": {
            "properties": {},
            "title": "list_bible_translationsArguments",
            "type": "object"
          },
          "annotations": null
        },
        {
          "name": "list_bible_books",
          "description": "\n    Get list of books for a specific Bible translation.\n\n    Args:\n        translation: Translation identifier (default: \"web\")\n\n    Returns:\n        List of books with their identifiers and names\n    ",
          "input_schema": {
            "properties": {
              "translation": {
                "default": "web",
                "title": "Translation",
                "type": "string"
              }
            },
            "title": "list_bible_booksArguments",
            "type": "object"
          },
          "annotations": null
        },
        {
          "name": "list_bible_chapters",
          "description": "\n    Get chapters for a specific Bible book.\n\n    Args:\n        book: Book identifier (e.g., \"JHN\" for John, \"GEN\" for Genesis)\n        translation: Translation identifier (default: \"web\")\n\n    Returns:\n        List of chapters for the specified book\n    ",
          "input_schema": {
            "properties": {
              "book": {
                "title": "Book",
                "type": "string"
              },
              "translation": {
                "default": "web",
                "title": "Translation",
                "type": "string"
              }
            },
            "required": [
              "book"
            ],
            "title": "list_bible_chaptersArguments",
            "type": "object"
          },
          "annotations": null
        }
      ],
      "tool_count": 5,
      "tool_names": [
        "get_random_bible_verse",
        "get_bible_verse",
        "list_bible_translations",
        "list_bible_books",
        "list_bible_chapters"
      ]
    },
    "server_info_crawled": {
      "id": 462,
      "name": "Bible Verse Access Server",
      "author": "@HarunGuclu/bible-mcp",
      "overview": "Provide easy access to Bible verses, passages, and translations in multiple languages. Retrieve random or specific verses, browse books and chapters, and explore various Bible translations seamlessly. Enhance your applications with rich biblical content through a simple API interface.",
      "repository_url": "https://github.com/HarunGuclu/bible-mcp",
      "homepage": "https://smithery.ai/server/@HarunGuclu/bible-mcp",
      "remote_or_local": "Remote",
      "license": "Smithery",
      "usage_count": "40",
      "success_rate": "Not available",
      "tags": [
        "search",
        "web",
        "api",
        "mcp"
      ],
      "categories": [
        "search",
        "api"
      ],
      "file_path": "../crawler/smithery/@HarunGuclu_bible-mcp.json",
      "tools_count": 5,
      "tools": [
        {
          "name": "get_random_bible_verse",
          "description": "\n    Get a random Bible verse.\n\n    Args:\n        book_ids: Optional comma-separated list of book IDs (e.g., \"GEN,JHN\")\n                 or special strings \"OT\" (Old Testament) or \"NT\" (New Testament)\n\n    Returns:\n        Random verse data including reference, text, and translation info\n    ",
          "input_schema": {
            "properties": {
              "book_ids": {
                "default": null,
                "title": "Book Ids",
                "type": "string"
              }
            },
            "title": "get_random_bible_verseArguments",
            "type": "object"
          },
          "annotations": null
        },
        {
          "name": "get_bible_verse",
          "description": "\n    Get a specific Bible verse or passage.\n\n    Args:\n        reference: Bible reference (e.g., \"John 3:16\", \"Genesis 1:1-3\")\n        translation: Translation identifier (default: \"web\" for World English Bible)\n\n    Returns:\n        Verse data including reference, text, and translation info\n    ",
          "input_schema": {
            "properties": {
              "reference": {
                "title": "Reference",
                "type": "string"
              },
              "translation": {
                "default": "web",
                "title": "Translation",
                "type": "string"
              }
            },
            "required": [
              "reference"
            ],
            "title": "get_bible_verseArguments",
            "type": "object"
          },
          "annotations": null
        },
        {
          "name": "list_bible_translations",
          "description": "\n    Get list of all available Bible translations.\n\n    Returns:\n        List of available translations with their identifiers and names\n    ",
          "input_schema": {
            "properties": {},
            "title": "list_bible_translationsArguments",
            "type": "object"
          },
          "annotations": null
        },
        {
          "name": "list_bible_books",
          "description": "\n    Get list of books for a specific Bible translation.\n\n    Args:\n        translation: Translation identifier (default: \"web\")\n\n    Returns:\n        List of books with their identifiers and names\n    ",
          "input_schema": {
            "properties": {
              "translation": {
                "default": "web",
                "title": "Translation",
                "type": "string"
              }
            },
            "title": "list_bible_booksArguments",
            "type": "object"
          },
          "annotations": null
        },
        {
          "name": "list_bible_chapters",
          "description": "\n    Get chapters for a specific Bible book.\n\n    Args:\n        book: Book identifier (e.g., \"JHN\" for John, \"GEN\" for Genesis)\n        translation: Translation identifier (default: \"web\")\n\n    Returns:\n        List of chapters for the specified book\n    ",
          "input_schema": {
            "properties": {
              "book": {
                "title": "Book",
                "type": "string"
              },
              "translation": {
                "default": "web",
                "title": "Translation",
                "type": "string"
              }
            },
            "required": [
              "book"
            ],
            "title": "list_bible_chaptersArguments",
            "type": "object"
          },
          "annotations": null
        }
      ],
      "python_sdk": "import mcp\nfrom mcp.client.streamable_http import streamablehttp_client\nimport json\nimport base64\n\nsmithery_api_key = \"\"\nurl = f\"https://server.smithery.ai/@HarunGuclu/bible-mcp/mcp?api_key={smithery_api_key}\"\n\nasync def main():\n    # Connect to the server using HTTP client\n    async with streamablehttp_client(url) as (read_stream, write_stream, _):\n        async with mcp.ClientSession(read_stream, write_stream) as session:\n            # Initialize the connection\n            await session.initialize()\n            # List available tools\n            tools_result = await session.list_tools()\n            print(f\"Available tools: {', '.join([t.name for t in tools_result.tools])}\")\n\nif __name__ == \"__main__\":\n    import asyncio\n    asyncio.run(main())",
      "configuration_schema": "",
      "smithery_configuration_requirements": [],
      "python_sdk_config": "",
      "python_sdk_url": "https://server.smithery.ai/@HarunGuclu/bible-mcp/mcp?api_key={smithery_api_key}"
    },
    "source_filename": "0463.@HarunGuclu_bible-mcp_prepared.json",
    "processed_timestamp": 1753731940,
    "processing_mode": "smithery",
    "rank": 454
  }
}