{
  "labels": {
    "analysis": "The MCP Server \"Jimeng Image Generation Server\" provides AI-powered image generation capabilities through the Jimeng AI service. Its primary functionality is to generate images from text prompts, allowing users to customize parameters and receive direct image URLs for easy display. This integrates seamlessly into applications needing advanced AI image creation tools.",
    "reasoning": "The primary label \"AI/ML Tools\" is chosen because the server's core functionality revolves around generating images using AI, a key aspect of machine learning and artificial intelligence. The secondary label \"Content Creation\" is included because the tool is directly used for generating creative content (images). No custom label is needed as the functionality is well-covered by the predefined categories.",
    "primary_label": "AI/ML Tools",
    "secondary_labels": [
      "Content Creation"
    ],
    "custom_label": null,
    "is_connected": false,
    "is_remote_tool_valid": false,
    "featured_server": false
  },
  "metadata": {
    "server_id": 269,
    "server_name": "Jimeng Image Generation Server",
    "rank_by_usage": 270,
    "usage_count": "139",
    "original_file": "../crawler/smithery/@c-rick_jimeng-mcp.json",
    "mode": "smithery",
    "timestamp": 1751941824,
    "remote_server_response": {
      "url": "https://server.smithery.ai/@c-rick/jimeng-mcp/mcp?api_key=8675feae-43b6-4170-beb5-d8fa5a938222&profile=monetary-anteater-CCaAaT",
      "is_success": false,
      "error": "unhandled errors in a TaskGroup (1 sub-exception)",
      "tools": [],
      "tool_count": 0,
      "tool_names": []
    },
    "server_info_crawled": {
      "id": 269,
      "name": "Jimeng Image Generation Server",
      "author": "@c-rick/jimeng-mcp",
      "overview": "Provide AI-powered image generation capabilities integrated with the Jimeng AI service. Generate images from text prompts with customizable parameters and receive direct image URLs for easy display. Enhance your applications with seamless access to advanced AI image creation tools.",
      "repository_url": "https://github.com/c-rick/jimeng-mcp",
      "homepage": "https://smithery.ai/server/@c-rick/jimeng-mcp",
      "remote_or_local": "Remote",
      "license": "Smithery",
      "usage_count": "139",
      "success_rate": "99.54%",
      "tags": [
        "search",
        "web",
        "api",
        "mcp"
      ],
      "categories": [
        "search",
        "api"
      ],
      "file_path": "../crawler/smithery/@c-rick_jimeng-mcp.json",
      "tools_count": 2,
      "tools": [
        {
          "name": "hello",
          "description": "Deploy Server Jimeng Image Generation Server @c-rick/jimeng-mcp Try in Playground",
          "parameters": [
            {
              "name": "hello",
              "required": false,
              "type": "string"
            },
            {
              "name": "name",
              "required": true,
              "type": "string"
            }
          ]
        },
        {
          "name": "generateImage",
          "description": "Description not available",
          "parameters": [
            {
              "name": "height",
              "required": false,
              "type": "string"
            },
            {
              "name": "prompt",
              "required": true,
              "type": "string"
            },
            {
              "name": "filePath",
              "required": false,
              "type": "string"
            },
            {
              "name": "negative_prompt",
              "required": false,
              "type": "string"
            },
            {
              "name": "sample_strength",
              "required": false,
              "type": "string"
            }
          ]
        }
      ],
      "python_sdk": "import mcp\nfrom mcp.client.streamable_http import streamablehttp_client\nimport json\nimport base64\n\nsmithery_api_key = \"\"\nurl = f\"https://server.smithery.ai/@c-rick/jimeng-mcp/mcp?api_key={smithery_api_key}\"\n\nasync def main():\n    # Connect to the server using HTTP client\n    async with streamablehttp_client(url) as (read_stream, write_stream, _):\n        async with mcp.ClientSession(read_stream, write_stream) as session:\n            # Initialize the connection\n            await session.initialize()\n            # List available tools\n            tools_result = await session.list_tools()\n            print(f\"Available tools: {', '.join([t.name for t in tools_result.tools])}\")\n\nif __name__ == \"__main__\":\n    import asyncio\n    asyncio.run(main())",
      "configuration_schema": "",
      "smithery_configuration_requirements": [
        {
          "name": "JIMENG_API_TOKEN",
          "required": true,
          "description": "jimeng api token"
        }
      ],
      "python_sdk_config": "",
      "python_sdk_url": "https://server.smithery.ai/@c-rick/jimeng-mcp/mcp?api_key={smithery_api_key}"
    },
    "source_filename": "cf_0270.@c-rick_jimeng-mcp_prepared.json",
    "processed_timestamp": 1753731940,
    "processing_mode": "smithery",
    "rank": 266
  }
}