{
  "labels": {
    "analysis": "The MCP Server integrates Large Language Models with Frontapp, enabling automated management of customer communications. It provides tools to interact with conversations, contacts, teammates, accounts, and tags within Frontapp, allowing users to automate workflows and enhance customer support capabilities through natural language commands.",
    "reasoning": "The primary focus of this server is enhancing customer support by automating and managing interactions in Frontapp. This aligns well with the \"Communication Tools\" category. The server also has strong ties to managing customer accounts and contacts, which fits under \"Customer Relationship Management\" (CRM) functionality. The automation aspect further supports productivity enhancements.",
    "primary_label": "Communication Tools",
    "secondary_labels": [
      "E-commerce",
      "Daily Productivity"
    ],
    "custom_label": "Customer Support Automation",
    "is_connected": false,
    "is_remote_tool_valid": false,
    "featured_server": false
  },
  "metadata": {
    "server_id": 2424,
    "server_name": "Frontapp Integration Server",
    "rank_by_usage": 2425,
    "usage_count": "Not available",
    "original_file": "../crawler/smithery/@zqushair_frontapp-mcp.json",
    "mode": "smithery",
    "timestamp": 1751941824,
    "remote_server_response": {
      "url": "https://server.smithery.ai/@zqushair/frontapp-mcp/mcp?api_key=8675feae-43b6-4170-beb5-d8fa5a938222&profile=monetary-anteater-CCaAaT",
      "is_success": false,
      "error": "unhandled errors in a TaskGroup (1 sub-exception)",
      "tools": [],
      "tool_count": 0,
      "tool_names": []
    },
    "server_info_crawled": {
      "id": 2424,
      "name": "Frontapp Integration Server",
      "author": "@zqushair/frontapp-mcp",
      "overview": "Integrate your Large Language Models with Frontapp to manage customer communications seamlessly. Automate workflows and access conversation data using natural language commands, enhancing your customer support capabilities.",
      "repository_url": "https://github.com/zqushair/Frontapp-MCP",
      "homepage": "https://smithery.ai/server/@zqushair/frontapp-mcp",
      "remote_or_local": "Remote",
      "license": "Smithery",
      "usage_count": "Not available",
      "success_rate": "Not available",
      "tags": [
        "search",
        "web",
        "api",
        "mcp"
      ],
      "categories": [
        "search",
        "api"
      ],
      "file_path": "../crawler/smithery/@zqushair_frontapp-mcp.json",
      "tools_count": 18,
      "tools": [
        {
          "name": "get_conversations",
          "description": "Deploy Server Frontapp Integration Server @zqushair/frontapp-mcp Try in Playground get_conversations",
          "parameters": [
            {
              "name": "get_conversations",
              "required": false,
              "type": "string"
            }
          ]
        },
        {
          "name": "get_conversation",
          "description": "Deploy Server Frontapp Integration Server @zqushair/frontapp-mcp Try in Playground get_conversations",
          "parameters": [
            {
              "name": "status",
              "required": false,
              "type": "string"
            },
            {
              "name": "tag_id",
              "required": false,
              "type": "string"
            },
            {
              "name": "inbox_id",
              "required": false,
              "type": "string"
            },
            {
              "name": "page_token",
              "required": false,
              "type": "string"
            },
            {
              "name": "assignee_id",
              "required": false,
              "type": "string"
            }
          ]
        },
        {
          "name": "send_message",
          "description": "Send a message to a conversation",
          "parameters": [
            {
              "name": "send_message",
              "required": false,
              "type": "string"
            }
          ]
        },
        {
          "name": "add_comment",
          "description": "Add a comment to a conversation",
          "parameters": [
            {
              "name": "body",
              "required": true,
              "type": "string"
            },
            {
              "name": "author_id",
              "required": true,
              "type": "string"
            },
            {
              "name": "conversation_id",
              "required": true,
              "type": "string"
            }
          ]
        },
        {
          "name": "archive_conversation",
          "description": "Archive a conversation",
          "parameters": [
            {
              "name": "archive_conversation",
              "required": false,
              "type": "string"
            },
            {
              "name": "Archive",
              "required": false,
              "type": "string"
            },
            {
              "name": "a",
              "required": false,
              "type": "string"
            },
            {
              "name": "conversation",
              "required": false,
              "type": "string"
            },
            {
              "name": "conversation_id",
              "required": true,
              "type": "string"
            }
          ]
        },
        {
          "name": "assign_conversation",
          "description": "Assign a conversation to a teammate",
          "parameters": [
            {
              "name": "assignee_id",
              "required": true,
              "type": "string"
            },
            {
              "name": "conversation_id",
              "required": true,
              "type": "string"
            }
          ]
        },
        {
          "name": "get_contact",
          "description": "Get details of a specific contact",
          "parameters": [
            {
              "name": "get_contact",
              "required": false,
              "type": "string"
            },
            {
              "name": "contact_id",
              "required": true,
              "type": "string"
            }
          ]
        },
        {
          "name": "create_contact",
          "description": "Create a new contact in Frontapp",
          "parameters": [
            {
              "name": "create_contact",
              "required": false,
              "type": "string"
            }
          ]
        },
        {
          "name": "update_contact",
          "description": "Update an existing contact in Frontapp",
          "parameters": [
            {
              "name": "update_contact",
              "required": false,
              "type": "string"
            }
          ]
        },
        {
          "name": "get_teammates",
          "description": "Get a list of teammates from Frontapp",
          "parameters": [
            {
              "name": "limit",
              "required": false,
              "type": "string"
            },
            {
              "name": "page_token",
              "required": false,
              "type": "string"
            }
          ]
        },
        {
          "name": "get_teammate",
          "description": "Get details of a specific teammate",
          "parameters": [
            {
              "name": "get_teammates",
              "required": false,
              "type": "string"
            }
          ]
        },
        {
          "name": "get_accounts",
          "description": "Get a list of accounts from Frontapp",
          "parameters": [
            {
              "name": "q",
              "required": false,
              "type": "string"
            },
            {
              "name": "limit",
              "required": false,
              "type": "string"
            },
            {
              "name": "page_token",
              "required": false,
              "type": "string"
            }
          ]
        },
        {
          "name": "get_account",
          "description": "Get details of a specific account",
          "parameters": [
            {
              "name": "get_accounts",
              "required": false,
              "type": "string"
            }
          ]
        },
        {
          "name": "create_account",
          "description": "Create a new account in Frontapp",
          "parameters": [
            {
              "name": "create_account",
              "required": false,
              "type": "string"
            }
          ]
        },
        {
          "name": "update_account",
          "description": "Update an existing account in Frontapp",
          "parameters": [
            {
              "name": "update_account",
              "required": false,
              "type": "string"
            }
          ]
        },
        {
          "name": "get_tags",
          "description": "Get a list of tags from Frontapp",
          "parameters": [
            {
              "name": "limit",
              "required": false,
              "type": "string"
            },
            {
              "name": "page_token",
              "required": false,
              "type": "string"
            }
          ]
        },
        {
          "name": "apply_tag",
          "description": "Apply a tag to a conversation",
          "parameters": [
            {
              "name": "tag_id",
              "required": true,
              "type": "string"
            },
            {
              "name": "conversation_id",
              "required": true,
              "type": "string"
            }
          ]
        },
        {
          "name": "remove_tag",
          "description": "Remove a tag from a conversation",
          "parameters": [
            {
              "name": "tag_id",
              "required": true,
              "type": "string"
            },
            {
              "name": "conversation_id",
              "required": true,
              "type": "string"
            }
          ]
        }
      ],
      "python_sdk": "import mcp\nfrom mcp.client.streamable_http import streamablehttp_client\nimport json\nimport base64\n\nsmithery_api_key = \"\"\nurl = f\"https://server.smithery.ai/@zqushair/frontapp-mcp/mcp?api_key={smithery_api_key}\"\n\nasync def main():\n    # Connect to the server using HTTP client\n    async with streamablehttp_client(url) as (read_stream, write_stream, _):\n        async with mcp.ClientSession(read_stream, write_stream) as session:\n            # Initialize the connection\n            await session.initialize()\n            # List available tools\n            tools_result = await session.list_tools()\n            print(f\"Available tools: {', '.join([t.name for t in tools_result.tools])}\")\n\nif __name__ == \"__main__\":\n    import asyncio\n    asyncio.run(main())",
      "configuration_schema": "",
      "smithery_configuration_requirements": [
        {
          "name": "webhookSecret",
          "required": true,
          "description": "Secret for verifying webhook signatures."
        },
        {
          "name": "frontappApiKey",
          "required": true,
          "description": "Your Frontapp API key."
        }
      ],
      "python_sdk_config": "",
      "python_sdk_url": "https://server.smithery.ai/@zqushair/frontapp-mcp/mcp?api_key={smithery_api_key}"
    },
    "source_filename": "cf_2425.@zqushair_frontapp-mcp_prepared.json",
    "processed_timestamp": 1753731940,
    "processing_mode": "smithery",
    "rank": 2071
  }
}