{
  "labels": {
    "analysis": "The MCP Server described is focused on integrating with Logseq, a personal knowledge management and note-taking application that uses a knowledge graph structure. The available tools allow users to interact with their Logseq notes, journals, and blocks in various ways—retrieving, analyzing, and managing content. The primary functionality involves organizing, querying, and deriving insights from personal knowledge graphs, making it a powerful tool for productivity, research, and personal knowledge management.",
    "reasoning": "The primary label is \"Memory Management\" because the server's core functionality revolves around organizing, querying, and managing notes and journals, which aligns with data storage and retrieval. \"Daily Productivity\" is a secondary label because enhancing personal productivity is a key use case. \"Content Creation\" is also relevant due to tools that help generate insights and connections from notes.",
    "primary_label": "Memory Management",
    "secondary_labels": [
      "Daily Productivity",
      "Content Creation"
    ],
    "custom_label": "Logseq Integration",
    "is_connected": false,
    "is_remote_tool_valid": false,
    "featured_server": false
  },
  "metadata": {
    "server_id": 428,
    "server_name": "Logseq Tools",
    "rank_by_usage": 429,
    "usage_count": "50",
    "original_file": "../crawler/smithery/@joelhooks_logseq-mcp-tools.json",
    "mode": "smithery",
    "timestamp": 1751941824,
    "remote_server_response": {
      "url": "https://server.smithery.ai/@joelhooks/logseq-mcp-tools/mcp?api_key=8675feae-43b6-4170-beb5-d8fa5a938222&profile=monetary-anteater-CCaAaT",
      "is_success": false,
      "error": "unhandled errors in a TaskGroup (1 sub-exception)",
      "tools": [],
      "tool_count": 0,
      "tool_names": []
    },
    "server_info_crawled": {
      "id": 428,
      "name": "Logseq Tools",
      "author": "@joelhooks/logseq-mcp-tools",
      "overview": "Integrate your Logseq knowledge graph with AI assistants. Retrieve, analyze, and manage your notes and journal entries effortlessly. Enhance your productivity by exploring connections and generating insights from your data.",
      "repository_url": "https://github.com/joelhooks/logseq-mcp-tools",
      "homepage": "https://smithery.ai/server/@joelhooks/logseq-mcp-tools",
      "remote_or_local": "Remote",
      "license": "Smithery",
      "usage_count": "50",
      "success_rate": "Not available",
      "tags": [
        "search",
        "web",
        "api",
        "mcp"
      ],
      "categories": [
        "search",
        "api"
      ],
      "file_path": "../crawler/smithery/@joelhooks_logseq-mcp-tools.json",
      "tools_count": 16,
      "tools": [
        {
          "name": "getAllPages",
          "description": "Deploy Server Logseq Tools Claim Server @joelhooks/logseq-mcp-tools Try in Playground getAllPages",
          "parameters": [
            {
              "name": "getAllPages",
              "required": false,
              "type": "string"
            }
          ]
        },
        {
          "name": "getPage",
          "description": "Description not available",
          "parameters": [
            {
              "name": "getPage",
              "required": false,
              "type": "string"
            },
            {
              "name": "pageName",
              "required": true,
              "type": "string"
            }
          ]
        },
        {
          "name": "getJournalSummary",
          "description": "Description not available",
          "parameters": [
            {
              "name": "getJournalSummary",
              "required": false,
              "type": "string"
            },
            {
              "name": "dateRange",
              "required": true,
              "type": "string"
            }
          ]
        },
        {
          "name": "createPage",
          "description": "Description not available",
          "parameters": [
            {
              "name": "createPage",
              "required": false,
              "type": "string"
            },
            {
              "name": "content",
              "required": false,
              "type": "string"
            },
            {
              "name": "pageName",
              "required": true,
              "type": "string"
            }
          ]
        },
        {
          "name": "searchPages",
          "description": "Description not available",
          "parameters": [
            {
              "name": "searchPages",
              "required": false,
              "type": "string"
            },
            {
              "name": "query",
              "required": true,
              "type": "string"
            }
          ]
        },
        {
          "name": "getBacklinks",
          "description": "Description not available",
          "parameters": [
            {
              "name": "getBacklinks",
              "required": false,
              "type": "string"
            },
            {
              "name": "pageName",
              "required": true,
              "type": "string"
            }
          ]
        },
        {
          "name": "addJournalEntry",
          "description": "Description not available",
          "parameters": [
            {
              "name": "date",
              "required": false,
              "type": "string"
            },
            {
              "name": "asBlock",
              "required": false,
              "type": "string"
            },
            {
              "name": "True",
              "required": false,
              "type": "string"
            },
            {
              "name": "False",
              "required": false,
              "type": "string"
            },
            {
              "name": "content",
              "required": true,
              "type": "string"
            }
          ]
        },
        {
          "name": "analyzeGraph",
          "description": "Description not available",
          "parameters": [
            {
              "name": "analyzeGraph",
              "required": false,
              "type": "string"
            },
            {
              "name": "daysThreshold",
              "required": false,
              "type": "string"
            }
          ]
        },
        {
          "name": "findKnowledgeGaps",
          "description": "Description not available",
          "parameters": [
            {
              "name": "includeOrphans",
              "required": false,
              "type": "string"
            },
            {
              "name": "True",
              "required": false,
              "type": "string"
            },
            {
              "name": "False",
              "required": false,
              "type": "string"
            },
            {
              "name": "minReferenceCount",
              "required": false,
              "type": "string"
            }
          ]
        },
        {
          "name": "analyzeJournalPatterns",
          "description": "Description not available",
          "parameters": [
            {
              "name": "True",
              "required": false,
              "type": "string"
            },
            {
              "name": "False",
              "required": false,
              "type": "string"
            },
            {
              "name": "includeTopics",
              "required": false,
              "type": "string"
            }
          ]
        },
        {
          "name": "smartQuery",
          "description": "Description not available",
          "parameters": [
            {
              "name": "True",
              "required": false,
              "type": "string"
            },
            {
              "name": "False",
              "required": false,
              "type": "string"
            },
            {
              "name": "includeQuery",
              "required": false,
              "type": "string"
            }
          ]
        },
        {
          "name": "suggestConnections",
          "description": "Description not available",
          "parameters": [
            {
              "name": "suggestConnections",
              "required": false,
              "type": "string"
            },
            {
              "name": "focusArea",
              "required": false,
              "type": "string"
            },
            {
              "name": "minConfidence",
              "required": false,
              "type": "string"
            },
            {
              "name": "maxSuggestions",
              "required": false,
              "type": "string"
            }
          ]
        },
        {
          "name": "addJournalBlock",
          "description": "Description not available",
          "parameters": [
            {
              "name": "date",
              "required": false,
              "type": "string"
            },
            {
              "name": "content",
              "required": true,
              "type": "string"
            },
            {
              "name": "preserveFormatting",
              "required": false,
              "type": "string"
            },
            {
              "name": "True",
              "required": false,
              "type": "string"
            },
            {
              "name": "False",
              "required": false,
              "type": "string"
            }
          ]
        },
        {
          "name": "addJournalContent",
          "description": "Description not available",
          "parameters": [
            {
              "name": "addJournalContent",
              "required": false,
              "type": "string"
            },
            {
              "name": "date",
              "required": false,
              "type": "string"
            },
            {
              "name": "content",
              "required": true,
              "type": "string"
            }
          ]
        },
        {
          "name": "addNoteContent",
          "description": "Description not available",
          "parameters": [
            {
              "name": "content",
              "required": true,
              "type": "string"
            },
            {
              "name": "pageName",
              "required": true,
              "type": "string"
            },
            {
              "name": "createIfNotExist",
              "required": false,
              "type": "string"
            },
            {
              "name": "True",
              "required": false,
              "type": "string"
            },
            {
              "name": "False",
              "required": false,
              "type": "string"
            }
          ]
        },
        {
          "name": "getBlock",
          "description": "Description not available",
          "parameters": [
            {
              "name": "blockId",
              "required": true,
              "type": "string"
            },
            {
              "name": "includeChildren",
              "required": false,
              "type": "string"
            },
            {
              "name": "True",
              "required": false,
              "type": "string"
            },
            {
              "name": "False",
              "required": false,
              "type": "string"
            }
          ]
        }
      ],
      "python_sdk": "import mcp\nfrom mcp.client.streamable_http import streamablehttp_client\nimport json\nimport base64\n\nsmithery_api_key = \"\"\nurl = f\"https://server.smithery.ai/@joelhooks/logseq-mcp-tools/mcp?api_key={smithery_api_key}\"\n\nasync def main():\n    # Connect to the server using HTTP client\n    async with streamablehttp_client(url) as (read_stream, write_stream, _):\n        async with mcp.ClientSession(read_stream, write_stream) as session:\n            # Initialize the connection\n            await session.initialize()\n            # List available tools\n            tools_result = await session.list_tools()\n            print(f\"Available tools: {', '.join([t.name for t in tools_result.tools])}\")\n\nif __name__ == \"__main__\":\n    import asyncio\n    asyncio.run(main())",
      "configuration_schema": "",
      "smithery_configuration_requirements": [
        {
          "name": "logseqToken",
          "required": true,
          "description": "Your Logseq HTTP API auth token"
        }
      ],
      "python_sdk_config": "",
      "python_sdk_url": "https://server.smithery.ai/@joelhooks/logseq-mcp-tools/mcp?api_key={smithery_api_key}"
    },
    "source_filename": "cf_0429.@joelhooks_logseq-mcp-tools_prepared.json",
    "processed_timestamp": 1753731940,
    "processing_mode": "smithery",
    "rank": 423
  }
}